Workbook

Sheet Vezetői összefoglaló
A1: Aurora Dynamics Kft. – 2025. évi vezetői összefoglaló
A2: Kiemelt pénzügyi mutatók – élő hivatkozással az Eredménykimutatás és a Cash flow kimutatás munkalapokra
A4: Nettó árbevétel | D4: EBITDA | G4: EBIT (üzemi eredmény) | J4: Adózott eredmény | M4: Operatív cash flow | P4: Záró pénzkészlet | S4: EBITDA-marzs | V4: Nettó eredményhányad
A5: =Eredménykimutatás!F6 -> 46971500 | D5: =Eredménykimutatás!F12 -> 23721500 | G5: =Eredménykimutatás!F14 -> 22821500 | J5: =Eredménykimutatás!F18 -> 20813065 | M5: ='Cash flow kimutatás'!F13 -> 21013065 | P5: ='Cash flow kimutatás'!F25 -> 23313065 | S5: =Eredménykimutatás!F20 -> 0.505019 | V5: =Eredménykimutatás!F21 -> 0.44309986
A7: Negyedév | B7: Árbevétel (Ft) | C7: EBITDA (Ft) | D7: EBIT (Ft) | E7: Adózott eredmény (Ft) | F7: Záró pénzkészlet (Ft)
A8: I. negyedév | B8: =Eredménykimutatás!B6 -> 10303500 | C8: =Eredménykimutatás!B12 -> 4808500 | D8: =Eredménykimutatás!B14 -> 4583500 | E8: =Eredménykimutatás!B18 -> 4175535 | F8: ='Cash flow kimutatás'!B25 -> 12420535
A9: II. negyedév | B9: =Eredménykimutatás!C6 -> 11425000 | C9: =Eredménykimutatás!C12 -> 5580000 | D9: =Eredménykimutatás!C14 -> 5355000 | E9: =Eredménykimutatás!C18 -> 4882150 | F9: ='Cash flow kimutatás'!C25 -> 17122685
A10: III. negyedév | B10: =Eredménykimutatás!D6 -> 11958000 | C10: =Eredménykimutatás!D12 -> 6113000 | D10: =Eredménykimutatás!D14 -> 5888000 | E10: =Eredménykimutatás!D18 -> 5371730 | F10: ='Cash flow kimutatás'!D25 -> 22389415
A11: IV. negyedév | B11: =Eredménykimutatás!E6 -> 13285000 | C11: =Eredménykimutatás!E12 -> 7220000 | D11: =Eredménykimutatás!E14 -> 6995000 | E11: =Eredménykimutatás!E18 -> 6383650 | F11: ='Cash flow kimutatás'!E25 -> 23313065
A12: 2025. évi összesen | B12: =Eredménykimutatás!F6 -> 46971500 | C12: =Eredménykimutatás!F12 -> 23721500 | D12: =Eredménykimutatás!F14 -> 22821500 | E12: =Eredménykimutatás!F18 -> 20813065 | F12: ='Cash flow kimutatás'!F25 -> 23313065
A14: A táblázat és a fenti mutatók minden cellája az Eredménykimutatás és a Cash flow kimutatás munkalapokra mutató élő hivatkozás; a részletes levezetés ott tekinthető meg.

Sheet Eredménykimutatás
A1: Aurora Dynamics Kft. – 2025. évi teljes pénzügyi jelentés
A2: Eredménykimutatás (összköltség eljárással, egyszerűsített séma)
A3: Az árbevétel- és költségsorok forrása: a 2025. évi bevételi és kiadási jelentés; az écs és a pénzügyi eredmény becsült érték – lásd a Feltételezések munkalapot.
A5: Megnevezés | B5: I. negyedév | C5: II. negyedév | D5: III. negyedév | E5: IV. negyedév | F5: 2025. évi összesen
A6: Nettó árbevétel | B6: 10303500 | C6: 11425000 | D6: 11958000 | E6: 13285000 | F6: =SUM(B6:E6) -> 46971500
A7: Üzemi költségek és ráfordítások:
A8: Személyi jellegű ráfordítások (bér- és járulékköltség) | B8: 3950000 | C8: 4120000 | D8: 4220000 | E8: 4310000 | F8: =SUM(B8:E8) -> 16600000
A9: Igénybe vett szolgáltatások (alvállalkozói díjak) | B9: 820000 | C9: 970000 | D9: 855000 | E9: 920000 | F9: =SUM(B9:E9) -> 3565000
A10: Egyéb anyagjellegű ráfordítások (szoftverlicenc, felhőinfrastruktúra, utazás, képzés) | B10: 725000 | C10: 755000 | D10: 770000 | E10: 835000 | F10: =SUM(B10:E10) -> 3085000
A11: Üzemi költségek és ráfordítások összesen (écs nélkül) | B11: =B8+B9+B10 -> 5495000 | C11: =C8+C9+C10 -> 5845000 | D11: =D8+D9+D10 -> 5845000 | E11: =E8+E9+E10 -> 6065000 | F11: =F8+F9+F10 -> 23250000
A12: EBITDA (kamat-, adó- és écs-fizetés előtti eredmény) | B12: =B6-B11 -> 4808500 | C12: =C6-C11 -> 5580000 | D12: =D6-D11 -> 6113000 | E12: =E6-E11 -> 7220000 | F12: =F6-F11 -> 23721500
A13: Értékcsökkenési leírás (écs) | B13: 225000 | C13: 225000 | D13: 225000 | E13: 225000 | F13: =SUM(B13:E13) -> 900000
A14: Üzemi (üzleti) tevékenység eredménye (EBIT) | B14: =B12-B13 -> 4583500 | C14: =C12-C13 -> 5355000 | D14: =D12-D13 -> 5888000 | E14: =E12-E13 -> 6995000 | F14: =F12-F13 -> 22821500
A15: Pénzügyi műveletek eredménye (kamatbevétel – banki költségek) | B15: 5000 | C15: 10000 | D15: 15000 | E15: 20000 | F15: =SUM(B15:E15) -> 50000
A16: Adózás előtti eredmény | B16: =B14+B15 -> 4588500 | C16: =C14+C15 -> 5365000 | D16: =D14+D15 -> 5903000 | E16: =E14+E15 -> 7015000 | F16: =F14+F15 -> 22871500
A17: Társasági adó (9%) | B17: =B16*0.09 -> 412965 | C17: =C16*0.09 -> 482850 | D17: =D16*0.09 -> 531270 | E17: =E16*0.09 -> 631350 | F17: =F16*0.09 -> 2058435
A18: Adózott eredmény | B18: =B16-B17 -> 4175535 | C18: =C16-C17 -> 4882150 | D18: =D16-D17 -> 5371730 | E18: =E16-E17 -> 6383650 | F18: =F16-F17 -> 20813065
A20: EBITDA-marzs (EBITDA / árbevétel) | B20: =B12/B6 -> 0.46668608 | C20: =C12/C6 -> 0.48840263 | D20: =D12/D6 -> 0.51120589 | E20: =E12/E6 -> 0.54347008 | F20: =F12/F6 -> 0.505019
A21: Nettó eredményhányad (adózott eredmény / árbevétel) | B21: =B18/B6 -> 0.40525404 | C21: =C18/C6 -> 0.42732166 | D21: =D18/D6 -> 0.44921642 | E21: =E18/E6 -> 0.48051562 | F21: =F18/F6 -> 0.44309986

Sheet Cash flow kimutatás
A1: Aurora Dynamics Kft. – 2025. évi teljes pénzügyi jelentés
A2: Cash flow kimutatás (indirekt módszerrel)
A3: Az adózott eredmény és az écs sora közvetlen hivatkozással az Eredménykimutatás munkalapról származik; a forgótőke-, beruházási és finanszírozási tételek becsült értékek – lásd a Feltételezések munkalapot.
A5: Megnevezés | B5: I. negyedév | C5: II. negyedév | D5: III. negyedév | E5: IV. negyedév | F5: 2025. évi összesen
A6: Működési (operatív) cash flow
A7: Adózott eredmény (Eredménykimutatás alapján) | B7: =Eredménykimutatás!B18 -> 4175535 | C7: =Eredménykimutatás!C18 -> 4882150 | D7: =Eredménykimutatás!D18 -> 5371730 | E7: =Eredménykimutatás!E18 -> 6383650 | F7: =Eredménykimutatás!F18 -> 20813065
A8: Écs visszaírása (nem pénzmozgású tétel) | B8: =Eredménykimutatás!B13 -> 225000 | C8: =Eredménykimutatás!C13 -> 225000 | D8: =Eredménykimutatás!D13 -> 225000 | E8: =Eredménykimutatás!E13 -> 225000 | F8: =Eredménykimutatás!F13 -> 900000
A9: Vevőkövetelések állományváltozása | B9: -350000 | C9: -300000 | D9: -280000 | E9: -420000 | F9: =SUM(B9:E9) -> -1350000
A10: Szállítói kötelezettségek állományváltozása | B10: 150000 | C10: 130000 | D10: 140000 | E10: 160000 | F10: =SUM(B10:E10) -> 580000
A11: Egyéb rövid lejáratú tételek változása | B11: 20000 | C11: 15000 | D11: 10000 | E11: 25000 | F11: =SUM(B11:E11) -> 70000
A12: Forgótőke-változás összesen | B12: =B9+B10+B11 -> -180000 | C12: =C9+C10+C11 -> -155000 | D12: =D9+D10+D11 -> -130000 | E12: =E9+E10+E11 -> -235000 | F12: =F9+F10+F11 -> -700000
A13: Működési (operatív) cash flow összesen | B13: =B7+B8+B12 -> 4220535 | C13: =C7+C8+C12 -> 4952150 | D13: =D7+D8+D12 -> 5466730 | E13: =E7+E8+E12 -> 6373650 | F13: =F7+F8+F12 -> 21013065
A15: Befektetési cash flow
A16: Tárgyi eszközök beszerzése (IT-eszközök, szerverek) | B16: -300000 | C16: -250000 | D16: -200000 | E16: -450000 | F16: =SUM(B16:E16) -> -1200000
A17: Befektetési cash flow összesen | B17: =B16 -> -300000 | C17: =C16 -> -250000 | D17: =D16 -> -200000 | E17: =E16 -> -450000 | F17: =F16 -> -1200000
A19: Finanszírozási cash flow
A20: Osztalékfizetés a tulajdonosok részére | B20: 0 | C20: 0 | D20: 0 | E20: -5000000 | F20: =SUM(B20:E20) -> -5000000
A21: Finanszírozási cash flow összesen | B21: =B20 -> 0 | C21: =C20 -> 0 | D21: =D20 -> 0 | E21: =E20 -> -5000000 | F21: =F20 -> -5000000
A23: Pénzeszközök nettó változása | B23: =B13+B17+B21 -> 3920535 | C23: =C13+C17+C21 -> 4702150 | D23: =D13+D17+D21 -> 5266730 | E23: =E13+E17+E21 -> 923650 | F23: =F13+F17+F21 -> 14813065
A24: Nyitó pénzkészlet | B24: 8500000 | C24: =B25 -> 12420535 | D24: =C25 -> 17122685 | E24: =D25 -> 22389415 | F24: =B24 -> 8500000
A25: Záró pénzkészlet | B25: =B24+B23 -> 12420535 | C25: =C24+C23 -> 17122685 | D25: =D24+D23 -> 22389415 | E25: =E24+E23 -> 23313065 | F25: =E25 -> 23313065

Sheet Feltételezések
A1: Aurora Dynamics Kft. – Feltételezések és források
A2: A 2025. évi teljes pénzügyi jelentés elkészítéséhez használt becslések és adatforrások
A4: Tétel | B4: Feltételezés / forrás
A5: Nettó árbevétel és üzemi költségek (bér, alvállalkozói díj, egyéb anyagjellegű) | B5: A 2025. évi bevételi és kiadási jelentés (Cloud integráció, Webfejlesztés, Tanácsadás munkalapok) szolgáltatásonkénti és negyedéves tételes adatai alapján, kategóriánként összesítve.
A6: Értékcsökkenési leírás (écs) | B6: Becsült érték: irodai IT-eszközök (laptopok, monitorok, hálózati eszközök, szerverek) lineáris écs-je, negyedévente egyenlő ütemben elszámolva (225 000 Ft/negyedév, éves szinten 900 000 Ft).
A7: Pénzügyi műveletek eredménye | B7: Becsült kamatbevétel a vállalati bankszámlán tartott pénzeszközök után, banki költségekkel csökkentve; a pénzkészlet negyedéves növekedésével arányosan emelkedő tétel.
A8: Társasági adó mértéke | B8: 9%, a Magyarországon jelenleg hatályos társasági adókulcs, egyéb adóalap-korrekció nélkül.
A9: Vevőkövetelések és szállítói kötelezettségek állományváltozása | B9: Becsült érték, amely a bevétel negyedéves növekedéséhez igazodik (a kintlévőségek az árbevétellel arányosan nőnek, a szállítói kötelezettségek mérsékeltebb ütemben).
A10: Tárgyi eszközök beszerzése (capex) | B10: Becsült éves beruházási keret informatikai eszközökre (laptopok, szerverek), negyedévenként eltérő ütemezéssel, összhangban az écs alapjául szolgáló eszközállománnyal.
A11: Osztalékfizetés | B11: Feltételezett egyszeri, IV. negyedévi tulajdonosi osztalékkifizetés (5 000 000 Ft).
A12: Nyitó pénzkészlet (2025.01.01) | B12: Feltételezett kezdő pénzeszköz-állomány: 8 500 000 Ft.
A14: Megjegyzés: a jelentés vezetői tájékoztatásra készült, nem minősül hivatalos, könyvvizsgáló által ellenőrzött beszámolónak.
